Workbook

Sheet Mode d'emploi
A1: Atelier fit-gap : standard Dynamics 365 Sales / pratique actuelle
A2: ARCHIA365, formation Dynamics 365 Sales niveau PO / BA
A4: Objectif | B4: Qualifier chaque étape du processus commercial par rapport au standard, puis prioriser les écarts.
A5: Atelier 1 (jour 1) | B5: Compléter l'onglet « Grille Hager » pour les étapes lead à facture, en s'appuyant sur le corrigé ARCHIFRIDAYS. Sous-groupe Diffuse et sous-groupe Project ; la colonne « Pratique actuelle Hager » est pré-remplie avec les sujets transmis par Hager, à confirmer ou corriger.
A6: Atelier 2 (jour 2) | B6: Compléter les étapes restantes, noter impact et effort, lire la priorité calculée et l'onglet « Synthèse ».
A7: Cellules à saisir | B7: Fond jaune : pratique actuelle, qualification, implication, impact, effort, commentaire.
A8: Qualification | B8: Conforme : on suit le standard. Écart justifié : l'écart répond à une contrainte réelle. Écart à questionner : l'écart doit être revu.
A9: Impact métier (1 à 5) | B9: 1 = gêne mineure, 5 = effet direct sur le chiffre d'affaires, la prévision ou la conformité.
A10: Effort de retour au standard (1 à 5) | B10: 1 = paramétrage simple, 5 = reprise de données, refonte de processus, conduite du changement lourde.
A11: Priorité (calculée) | B11: Gain rapide : impact ≥ 4 et effort ≤ 2. Projet structurant : impact ≥ 4 et effort ≥ 3. Amélioration simple : impact ≤ 3 et effort ≤ 2. À reconsidérer : impact ≤ 3 et effort ≥ 3.

Sheet Corrigé ARCHIFRIDAYS
A1: Corrigé ARCHIFRIDAYS (modèle de réponse)
A3: Étape | B3: Standard Dynamics 365 Sales | C3: Pratique actuelle | D3: Qualification | E3: Implication | F3: Impact métier (1-5) | G3: Effort retour au standard (1-5) | H3: Priorité (calculée) | I3: Canal (Diffuse / Project) | J3: Commentaire
A4: Capture des leads | B4: Import avec campagne source, détection des doublons | C4: Trois sources (Eloqua, Lead App des salons, saisie manuelle), sans règle de source unique | D4: Écart à questionner | E4: Retour sur investissement des salons non mesuré, doublons entre outils | F4: 4 | G4: 1 | H4: =IF(OR(D4="",F4="",G4=""),"",IF(D4="Conforme","Aucune action",IF(AND(F4>=4,G4<=2),"Gain rapide",IF(AND(F4>=4,G4>=3),"Projet structurant",IF(G4<=2,"Amélioration simple","À reconsidérer"))))) -> Gain rapide | I4: Les deux
A5: Qualification | B5: Processus Lead to Opportunity, conversion en opportunité | C5: Entité lead récemment personnalisée, opportunité projet créée à la main | D5: Écart à questionner | E5: Double saisie, historique du lead perdu | F5: 4 | G5: 2 | H5: =IF(OR(D5="",F5="",G5=""),"",IF(D5="Conforme","Aucune action",IF(AND(F5>=4,G5<=2),"Gain rapide",IF(AND(F5>=4,G5>=3),"Projet structurant",IF(G5<=2,"Amélioration simple","À reconsidérer"))))) -> Gain rapide | I5: Les deux
A6: Compte | B6: Compte, hiérarchie de comptes, objectifs ; pas d'équivalent natif complet pour le plan de compte, la qualification par gamme ou la part de portefeuille | C6: Colonnes spécifiques sur le compte | D6: Écart justifié, à confirmer | E6: Désigner le propriétaire et la source des données (saisie, SAP, Power BI) | F6: 3 | G6: 3 | H6: =IF(OR(D6="",F6="",G6=""),"",IF(D6="Conforme","Aucune action",IF(AND(F6>=4,G6<=2),"Gain rapide",IF(AND(F6>=4,G6>=3),"Projet structurant",IF(G6<=2,"Amélioration simple","À reconsidérer"))))) -> À reconsidérer | I6: Diffuse
A7: Projet multi-acteurs | B7: Opportunité, parties prenantes, rôles de connexion, équipe commerciale, concurrents | C7: Table spécifique « Toile projet », en parallèle des parties prenantes | D7: Écart à questionner | E7: Intervenants invisibles pour Copilot et l'analyse des relations ; double saisie avec les parties prenantes | F7: 5 | G7: 4 | H7: =IF(OR(D7="",F7="",G7=""),"",IF(D7="Conforme","Aucune action",IF(AND(F7>=4,G7<=2),"Gain rapide",IF(AND(F7>=4,G7>=3),"Projet structurant",IF(G7<=2,"Amélioration simple","À reconsidérer"))))) -> Projet structurant | I7: Project
A8: Opportunité | B8: Opportunité standard et processus d'entreprise | C8: 140 colonnes spécifiques, un tiers vides, refonte en cours | D8: Écart à questionner | E8: La refonte est l'occasion de revenir au standard | F8: 5 | G8: 4 | H8: =IF(OR(D8="",F8="",G8=""),"",IF(D8="Conforme","Aucune action",IF(AND(F8>=4,G8<=2),"Gain rapide",IF(AND(F8>=4,G8>=3),"Projet structurant",IF(G8<=2,"Amélioration simple","À reconsidérer"))))) -> Projet structurant | I8: Project
A9: Visibilité des remises | B9: Profil de sécurité de colonne | C9: Profil de sécurité de colonne | D9: Conforme | E9: Aucune | F9: 2 | G9: 1 | H9: =IF(OR(D9="",F9="",G9=""),"",IF(D9="Conforme","Aucune action",IF(AND(F9>=4,G9<=2),"Gain rapide",IF(AND(F9>=4,G9>=3),"Projet structurant",IF(G9<=2,"Amélioration simple","À reconsidérer"))))) -> Aucune action | I9: Les deux
A10: Devis | B10: Devis natif, modèle Word, révisions | C10: Classeur Excel, ressaisi dans SAP par l'ADV | D10: Écart à questionner | E10: Erreurs de ressaisie, pas d'historique des versions | F10: 4 | G10: 3 | H10: =IF(OR(D10="",F10="",G10=""),"",IF(D10="Conforme","Aucune action",IF(AND(F10>=4,G10<=2),"Gain rapide",IF(AND(F10>=4,G10>=3),"Projet structurant",IF(G10<=2,"Amélioration simple","À reconsidérer"))))) -> Projet structurant | I10: Project
A11: Approbation des remises | B11: Non natif, extension Power Automate | C11: E-mail informel à la directrice | D11: Écart justifié | E11: Extension low-code à maintenir, traçabilité gagnée | F11: 3 | G11: 2 | H11: =IF(OR(D11="",F11="",G11=""),"",IF(D11="Conforme","Aucune action",IF(AND(F11>=4,G11<=2),"Gain rapide",IF(AND(F11>=4,G11>=3),"Projet structurant",IF(G11<=2,"Amélioration simple","À reconsidérer"))))) -> Amélioration simple | I11: Project
A12: Commande | B12: Commande générée depuis le devis gagné | C12: Saisie par l'ADV dans SAP | D12: Écart justifié | E12: Intégration CRM vers SAP à prévoir | F12: 3 | G12: 4 | H12: =IF(OR(D12="",F12="",G12=""),"",IF(D12="Conforme","Aucune action",IF(AND(F12>=4,G12<=2),"Gain rapide",IF(AND(F12>=4,G12>=3),"Projet structurant",IF(G12<=2,"Amélioration simple","À reconsidérer"))))) -> À reconsidérer | I12: Les deux
A13: Facture | B13: Table facture standard | C13: SAP uniquement | D13: Écart justifié | E13: Remonter le statut de facturation dans le CRM | F13: 2 | G13: 3 | H13: =IF(OR(D13="",F13="",G13=""),"",IF(D13="Conforme","Aucune action",IF(AND(F13>=4,G13<=2),"Gain rapide",IF(AND(F13>=4,G13>=3),"Projet structurant",IF(G13<=2,"Amélioration simple","À reconsidérer"))))) -> À reconsidérer | I13: Les deux
A14: Prévision | B14: Prévision native, objectifs ; historique via export vers Power BI | C14: Classeur Excel hebdomadaire consolidé à la main | D14: Écart à questionner | E14: Une journée de consolidation par semaine | F14: 5 | G14: 2 | H14: =IF(OR(D14="",F14="",G14=""),"",IF(D14="Conforme","Aucune action",IF(AND(F14>=4,G14<=2),"Gain rapide",IF(AND(F14>=4,G14>=3),"Projet structurant",IF(G14<=2,"Amélioration simple","À reconsidérer"))))) -> Gain rapide | I14: Les deux
A15: Interactions | B15: Synchronisation Exchange, complément Outlook | C15: E-mails dans les boîtes individuelles | D15: Écart à questionner | E15: Historique perdu au départ d'un commercial | F15: 4 | G15: 2 | H15: =IF(OR(D15="",F15="",G15=""),"",IF(D15="Conforme","Aucune action",IF(AND(F15>=4,G15<=2),"Gain rapide",IF(AND(F15>=4,G15>=3),"Projet structurant",IF(G15<=2,"Amélioration simple","À reconsidérer"))))) -> Gain rapide | I15: Les deux
A16: Rendez-vous | B16: Rendez-vous standard (objet, description, « Concernant »), préparation avec Copilot | C16: Colonne spécifique « Objectifs du rendez-vous » | D16: Écart justifié léger | E16: Vérifier que la colonne est exploitée après le rendez-vous | F16: 2 | G16: 1 | H16: =IF(OR(D16="",F16="",G16=""),"",IF(D16="Conforme","Aucune action",IF(AND(F16>=4,G16<=2),"Gain rapide",IF(AND(F16>=4,G16>=3),"Projet structurant",IF(G16<=2,"Amélioration simple","À reconsidérer"))))) -> Amélioration simple | I16: Diffuse

Sheet Grille Hager
A1: Grille fit-gap Hager
A2: Pré-remplie avec les sujets transmis par Hager (hypothèses à confirmer). Fond jaune = à compléter. La ligne 4 est un exemple.
A3: Étape | B3: Standard Dynamics 365 Sales | C3: Pratique actuelle Hager (hypothèse à confirmer) | D3: Qualification | E3: Implication | F3: Impact métier (1-5) | G3: Effort retour au standard (1-5) | H3: Priorité (calculée) | I3: Canal (Diffuse / Project) | J3: Commentaire
A4: Exemple : capture des leads | B4: Import avec campagne source, détection des doublons | C4: Leads salons saisis à la main par les commerciaux | D4: Écart à questionner | E4: Source des leads inconnue, pas de mesure du ROI | F4: 4 | G4: 1 | H4: =IF(OR(D4="",F4="",G4=""),"",IF(D4="Conforme","Aucune action",IF(AND(F4>=4,G4<=2),"Gain rapide",IF(AND(F4>=4,G4>=3),"Projet structurant",IF(G4<=2,"Amélioration simple","À reconsidérer"))))) -> Gain rapide | I4: Diffuse | J4: Ligne d'exemple
A5: Capture des leads | B5: Import avec campagne source, formulaires, détection des doublons | C5: Leads issus d'Eloqua, de la Lead App (salons) et de l'Event Management Tool ; règle de source à confirmer | H5: =IF(OR(D5="",F5="",G5=""),"",IF(D5="Conforme","Aucune action",IF(AND(F5>=4,G5<=2),"Gain rapide",IF(AND(F5>=4,G5>=3),"Projet structurant",IF(G5<=2,"Amélioration simple","À reconsidérer"))))) | I5: Les deux
A6: Qualification des leads | B6: Processus Lead to Opportunity : budget, délai, décideur, besoin | C6: Entité Lead récemment personnalisée : critères et règles à revoir ensemble | H6: =IF(OR(D6="",F6="",G6=""),"",IF(D6="Conforme","Aucune action",IF(AND(F6>=4,G6<=2),"Gain rapide",IF(AND(F6>=4,G6>=3),"Projet structurant",IF(G6<=2,"Amélioration simple","À reconsidérer"))))) | I6: Les deux
A7: Conversion en opportunité | B7: Création de l'opportunité, rattachement au compte et au contact | C7: À préciser : opportunité projet créée depuis le lead ou à la main ? | H7: =IF(OR(D7="",F7="",G7=""),"",IF(D7="Conforme","Aucune action",IF(AND(F7>=4,G7<=2),"Gain rapide",IF(AND(F7>=4,G7>=3),"Projet structurant",IF(G7<=2,"Amélioration simple","À reconsidérer"))))) | I7: Project
A8: Compte : plan de compte | B8: Pas d'équivalent natif complet : compte, objectifs, Power BI | C8: Account Plan spécifique | H8: =IF(OR(D8="",F8="",G8=""),"",IF(D8="Conforme","Aucune action",IF(AND(F8>=4,G8<=2),"Gain rapide",IF(AND(F8>=4,G8>=3),"Projet structurant",IF(G8<=2,"Amélioration simple","À reconsidérer"))))) | I8: Diffuse
A9: Compte : qualification client | B9: Pas d'équivalent natif : colonnes ou table liée par gamme | C9: Customer Qualification (fidélité par gamme, déclaratif) | H9: =IF(OR(D9="",F9="",G9=""),"",IF(D9="Conforme","Aucune action",IF(AND(F9>=4,G9<=2),"Gain rapide",IF(AND(F9>=4,G9>=3),"Projet structurant",IF(G9<=2,"Amélioration simple","À reconsidérer"))))) | I9: Diffuse
A10: Compte : part de portefeuille | B10: Pas d'équivalent natif : calcul Power BI avec données SAP | C10: Share of wallet spécifique | H10: =IF(OR(D10="",F10="",G10=""),"",IF(D10="Conforme","Aucune action",IF(AND(F10>=4,G10<=2),"Gain rapide",IF(AND(F10>=4,G10>=3),"Projet structurant",IF(G10<=2,"Amélioration simple","À reconsidérer"))))) | I10: Diffuse
A11: Intervenants du projet | B11: Parties prenantes, rôles de connexion, équipe commerciale, concurrents | C11: Project Spider (table spécifique des intervenants et de leur rôle) | H11: =IF(OR(D11="",F11="",G11=""),"",IF(D11="Conforme","Aucune action",IF(AND(F11>=4,G11<=2),"Gain rapide",IF(AND(F11>=4,G11>=3),"Projet structurant",IF(G11<=2,"Amélioration simple","À reconsidérer"))))) | I11: Project
A12: Opportunité | B12: Opportunité standard, processus Qualifier, Développer, Proposer, Conclure | C12: Entité entièrement personnalisée pour les projets ; refonte en cours | H12: =IF(OR(D12="",F12="",G12=""),"",IF(D12="Conforme","Aucune action",IF(AND(F12>=4,G12<=2),"Gain rapide",IF(AND(F12>=4,G12>=3),"Projet structurant",IF(G12<=2,"Amélioration simple","À reconsidérer"))))) | I12: Project
A13: Catalogue et prix | B13: Familles, unités, listes de prix, produits d'opportunité | C13: À préciser : catalogue et prix maîtres dans SAP ? | H13: =IF(OR(D13="",F13="",G13=""),"",IF(D13="Conforme","Aucune action",IF(AND(F13>=4,G13<=2),"Gain rapide",IF(AND(F13>=4,G13>=3),"Projet structurant",IF(G13<=2,"Amélioration simple","À reconsidérer"))))) | I13: Les deux
A14: Devis | B14: Devis natif, révisions, modèle Word | C14: Projets et devis interfacés avec SAP : sens des flux à préciser | H14: =IF(OR(D14="",F14="",G14=""),"",IF(D14="Conforme","Aucune action",IF(AND(F14>=4,G14<=2),"Gain rapide",IF(AND(F14>=4,G14>=3),"Projet structurant",IF(G14<=2,"Amélioration simple","À reconsidérer"))))) | I14: Project
A15: Commande et facture | B15: Commande depuis le devis gagné ; facture souvent dans l'ERP | C15: SAP : à préciser | H15: =IF(OR(D15="",F15="",G15=""),"",IF(D15="Conforme","Aucune action",IF(AND(F15>=4,G15<=2),"Gain rapide",IF(AND(F15>=4,G15>=3),"Projet structurant",IF(G15<=2,"Amélioration simple","À reconsidérer"))))) | I15: Les deux
A16: Rendez-vous | B16: Rendez-vous standard (objet, description, Concernant), préparation Copilot | C16: Meeting Objectives (colonne spécifique) | H16: =IF(OR(D16="",F16="",G16=""),"",IF(D16="Conforme","Aucune action",IF(AND(F16>=4,G16<=2),"Gain rapide",IF(AND(F16>=4,G16>=3),"Projet structurant",IF(G16<=2,"Amélioration simple","À reconsidérer"))))) | I16: Diffuse
... A23: Intégrations | B23: Connecteurs et API Dataverse | C23: SAP (comptes, projets, devis), Eloqua (leads, contacts), Power BI, data platform, Event Management Tool, Lead App | H23: =IF(OR(D23="",F23="",G23=""),"",IF(D23="Conforme","Aucune action",IF(AND(F23>=4,G23<=2),"Gain rapide",IF(AND(F23>=4,G23>=3),"Projet structurant",IF(G23<=2,"Amélioration simple","À reconsidérer"))))) | I23: Les deux
H24: =IF(OR(D24="",F24="",G24=""),"",IF(D24="Conforme","Aucune action",IF(AND(F24>=4,G24<=2),"Gain rapide",IF(AND(F24>=4,G24>=3),"Projet structurant",IF(G24<=2,"Amélioration simple","À reconsidérer")))))
H25: =IF(OR(D25="",F25="",G25=""),"",IF(D25="Conforme","Aucune action",IF(AND(F25>=4,G25<=2),"Gain rapide",IF(AND(F25>=4,G25>=3),"Projet structurant",IF(G25<=2,"Amélioration simple","À reconsidérer")))))
H26: =IF(OR(D26="",F26="",G26=""),"",IF(D26="Conforme","Aucune action",IF(AND(F26>=4,G26<=2),"Gain rapide",IF(AND(F26>=4,G26>=3),"Projet structurant",IF(G26<=2,"Amélioration simple","À reconsidérer")))))
H27: =IF(OR(D27="",F27="",G27=""),"",IF(D27="Conforme","Aucune action",IF(AND(F27>=4,G27<=2),"Gain rapide",IF(AND(F27>=4,G27>=3),"Projet structurant",IF(G27<=2,"Amélioration simple","À reconsidérer")))))
H28: =IF(OR(D28="",F28="",G28=""),"",IF(D28="Conforme","Aucune action",IF(AND(F28>=4,G28<=2),"Gain rapide",IF(AND(F28>=4,G28>=3),"Projet structurant",IF(G28<=2,"Amélioration simple","À reconsidérer")))))
H29: =IF(OR(D29="",F29="",G29=""),"",IF(D29="Conforme","Aucune action",IF(AND(F29>=4,G29<=2),"Gain rapide",IF(AND(F29>=4,G29>=3),"Projet structurant",IF(G29<=2,"Amélioration simple","À reconsidérer")))))

Sheet Synthèse
A1: Synthèse de la grille Hager (calculée)
A2: Exclut la ligne d'exemple (ligne 4).
A4: Qualification | B4: Nombre d'étapes
A5: Conforme | B5: =COUNTIF('Grille Hager'!$D$5:$D$29,A5) -> 0
A6: Écart justifié | B6: =COUNTIF('Grille Hager'!$D$5:$D$29,A6) -> 0
A7: Écart à questionner | B7: =COUNTIF('Grille Hager'!$D$5:$D$29,A7) -> 0
A8: Total qualifié | B8: =SUM(B5:B7) -> 0
A10: Priorité | B10: Nombre d'écarts
A11: Gain rapide | B11: =COUNTIF('Grille Hager'!$H$5:$H$29,A11) -> 0
A12: Projet structurant | B12: =COUNTIF('Grille Hager'!$H$5:$H$29,A12) -> 0
A13: Amélioration simple | B13: =COUNTIF('Grille Hager'!$H$5:$H$29,A13) -> 0
A14: À reconsidérer | B14: =COUNTIF('Grille Hager'!$H$5:$H$29,A14) -> 0
A15: Aucune action | B15: =COUNTIF('Grille Hager'!$H$5:$H$29,A15) -> 0
A17: Part des étapes conformes | B17: =IF(B8=0,0,B5/B8) -> 0
